compression_middleware/__init__.py
compression_middleware/br.py
compression_middleware/decorators.py
compression_middleware/middleware.py
compression_middleware/zstd.py
django_compression_middleware-0.5.0.dist-info/METADATA
django_compression_middleware-0.5.0.dist-info/WHEEL
django_compression_middleware-0.5.0.dist-info/top_level.txt
django_compression_middleware-0.5.0.dist-info/zip-safe
django_compression_middleware-0.5.0.dist-info/RECORD
